__init__.py
grammateus/__init__.py
grammateus/entities.py
grammateus/utilities.py
grammateus-0.1.3.dist-info/licenses/LICENSE
grammateus-0.1.3.dist-info/METADATA
grammateus-0.1.3.dist-info/WHEEL
grammateus-0.1.3.dist-info/top_level.txt
grammateus-0.1.3.dist-info/RECORD
