Metadata-Version: 2.4
Name: grammateus
Version: 0.1.3
Summary: A role responsible for documenting legal proceedings in Greece
Author-email: Alexander Fedotov <alex.fedotov@aol.com>
Project-URL: Homepage, https://github.com/multilogue/grammateus
Project-URL: Bug Tracker, https://github.com/multilogue/grammateus/issues
Keywords: grammateus,recording,ai
Classifier: Programming Language :: Python :: 3
Classifier: License :: OSI Approved :: MIT License
Classifier: Operating System :: OS Independent
Requires-Python: >=3.10
License-File: LICENSE
Requires-Dist: requests>=2.32.3
Requires-Dist: jsonlines>=4.0.0
Requires-Dist: PyYAML>=6.0.2
Provides-Extra: arrow
Requires-Dist: pyarrow>=20.0.0; extra == "arrow"
Dynamic: license-file
